aria_studio/__init__.py
aria_studio/logging.yml
aria_studio/main.py
aria_studio/app/__init__.py
aria_studio/app/constants.py
aria_studio/app/return_codes.py
aria_studio/app/singleton_base.py
aria_studio/app/utils.py
aria_studio/app/auth/__init__.py
aria_studio/app/auth/mma_login_helper.py
aria_studio/app/common/__init__.py
aria_studio/app/common/args.py
aria_studio/app/common/disk_cache.py
aria_studio/app/common/types.py
aria_studio/app/device/__init__.py
aria_studio/app/device/device_manager.py
aria_studio/app/groups/__init__.py
aria_studio/app/groups/group_manager.py
aria_studio/app/local/__init__.py
aria_studio/app/local/app_info.py
aria_studio/app/local/local_file_manager.py
aria_studio/app/local/local_log_manager.py
aria_studio/app/mps/__init__.py
aria_studio/app/mps/group_mps_request_cache.py
aria_studio/app/mps/group_mps_request_manager.py
aria_studio/app/mps/individual_mps_request_cache.py
aria_studio/app/mps/individual_mps_request_manager.py
aria_studio/app/routes/__init__.py
aria_studio/app/routes/app_routes.py
aria_studio/app/routes/auth_routes.py
aria_studio/app/routes/device_routes.py
aria_studio/app/routes/explorer_routes.py
aria_studio/app/routes/group_routes.py
aria_studio/app/routes/local_files_routes.py
aria_studio/app/routes/mps_routes.py
aria_studio/app/routes/root_routes.py
aria_studio/frontend/SourceSansPro-RyPo.ttf
aria_studio/frontend/asset-manifest.json
aria_studio/frontend/favicon.ico
aria_studio/frontend/index.html
aria_studio/frontend/static/css/main.be8e429d.css
aria_studio/frontend/static/css/main.be8e429d.css.map
aria_studio/frontend/static/js/main.fedd54b3.js
aria_studio/frontend/static/js/main.fedd54b3.js.LICENSE.txt
aria_studio/frontend/static/js/main.fedd54b3.js.map
aria_studio/frontend/static/media/AriaHorizontalLogo.df712a41c9bb0a8a4f35b52db376b4de.svg
aria_studio/frontend/static/media/Hero_Image_Landingpage.47dd61d1bd3621b04792.png
aria_studio/frontend/static/media/NoGroup.9c53fa53c0445370d1ddcacb9bdbfd0c.svg
aria_studio-1.1.1.dist-info/LICENSE
aria_studio-1.1.1.dist-info/METADATA
aria_studio-1.1.1.dist-info/WHEEL
aria_studio-1.1.1.dist-info/entry_points.txt
aria_studio-1.1.1.dist-info/top_level.txt
aria_studio-1.1.1.dist-info/zip-safe
aria_studio-1.1.1.dist-info/RECORD
