Metadata-Version: 2.1
Name: aria_studio
Version: 1.1.1
Summary: Aria Studio
Author: Meta Reality Labs Research
License: Apache-2.0
Requires-Python: >=3.11
License-File: LICENSE
Requires-Dist: aiofiles
Requires-Dist: aiohttp
Requires-Dist: aioredis
Requires-Dist: aiosqlite
Requires-Dist: annotated-types
Requires-Dist: anyio
Requires-Dist: async-timeout
Requires-Dist: attrs
Requires-Dist: certifi
Requires-Dist: charset-normalizer
Requires-Dist: click
Requires-Dist: dataclasses
Requires-Dist: dnspython
Requires-Dist: email-validator
Requires-Dist: exceptiongroup
Requires-Dist: fastapi-cache
Requires-Dist: fastapi-cli
Requires-Dist: fastapi
Requires-Dist: h11
Requires-Dist: hiredis
Requires-Dist: httpcore
Requires-Dist: httptools
Requires-Dist: httpx
Requires-Dist: idna
Requires-Dist: imageio
Requires-Dist: iniconfig
Requires-Dist: Jinja2
Requires-Dist: jsons
Requires-Dist: markdown-it-py
Requires-Dist: MarkupSafe
Requires-Dist: mdurl
Requires-Dist: numpy (>=1.24.4)
Requires-Dist: orjson
Requires-Dist: packaging
Requires-Dist: pillow
Requires-Dist: pluggy
Requires-Dist: projectaria-tools (==1.7.1)
Requires-Dist: pyarrow (>=10.0.1)
Requires-Dist: pydantic
Requires-Dist: pydantic-core
Requires-Dist: Pygments
Requires-Dist: pytest
Requires-Dist: pytest-asyncio
Requires-Dist: python-dotenv
Requires-Dist: pycryptodome
Requires-Dist: python-multipart
Requires-Dist: PyYAML
Requires-Dist: requests
Requires-Dist: rerun-sdk (==0.22.1)
Requires-Dist: rich
Requires-Dist: shellingham
Requires-Dist: sniffio
Requires-Dist: soupsieve (==2.5)
Requires-Dist: starlette
Requires-Dist: textual
Requires-Dist: tomli
Requires-Dist: tqdm
Requires-Dist: transitions
Requires-Dist: typer
Requires-Dist: typing
Requires-Dist: typing-extensions
Requires-Dist: typish
Requires-Dist: ujson
Requires-Dist: urllib3
Requires-Dist: uvicorn
Requires-Dist: watchfiles
Requires-Dist: websockets
Requires-Dist: xxhash
Requires-Dist: keyring
